{
  "2001": {
    "합계": 285224,
    "원자력": 112133,
    "화력": 168938,
    "수력": 4151,
    "신재생 및 기타": "NaN"
  },
  "2002": {
    "합계": 306474,
    "원자력": 119103,
    "화력": 182060,
    "수력": 5311,
    "신재생 및 기타": "NaN"
  },
  "2003": {
    "합계": 322452,
    "원자력": 129672,
    "화력": 185893,
    "수력": 6887,
    "신재생 및 기타": "NaN"
  },
  "2004": {
    "합계": 342148,
    "원자력": 130714,
    "화력": 201674,
    "수력": 5744,
    "신재생 및 기타": 4016
  },
  "2005": {
    "합계": 364639,
    "원자력": 146779,
    "화력": 209504,
    "수력": 5015,
    "신재생 및 기타": 3341
  },
  "2006": {
    "합계": 381181,
    "원자력": 148749,
    "화력": 226702,
    "수력": 1751,
    "신재생 및 기타": 3979
  },
  "2007": {
    "합계": 403125,
    "원자력": 142937,
    "화력": 254316,
    "수력": 1411,
    "신재생 및 기타": 4461
  },
  "2008": {
    "합계": 422355,
    "원자력": 150958,
    "화력": 264743,
    "수력": 2493,
    "신재생 및 기타": 4162
  },
  "2009": {
    "합계": 433604,
    "원자력": 147771,
    "화력": 278401,
    "수력": 2828,
    "신재생 및 기타": 4604
  },
  "2010": {
    "합계": 474660,
    "원자력": 148596,
    "화력": 314272,
    "수력": 2790,
    "신재생 및 기타": 9002
  },
  "2011": {
    "합계": 496893,
    "원자력": 154723,
    "화력": 326747,
    "수력": 3233,
    "신재생 및 기타": 12190
  },
  "2012": {
    "합계": 509574,
    "원자력": 150327,
    "화력": 342977,
    "수력": 3683,
    "신재생 및 기타": 12587
  },
  "2013": {
    "합계": 517148,
    "원자력": 138784,
    "화력": 359753,
    "수력": 4105,
    "신재생 및 기타": 14506
  },
  "2014": {
    "합계": 521971,
    "원자력": 156407,
    "화력": 343050,
    "수력": 5068,
    "신재생 및 기타": 17446
  },
  "2015": {
    "합계": 528091,
    "원자력": 164762,
    "화력": 336629,
    "수력": 3650,
    "신재생 및 기타": 23050
  },
  "2016": {
    "합계": 540441,
    "원자력": 161995,
    "화력": 348822,
    "수력": 3787,
    "신재생 및 기타": 25837
  },
  "2017": {
    "합계": 553530,
    "원자력": 148427,
    "화력": 369943,
    "수력": 4186,
    "신재생 및 기타": 30974
  },
  "2018": {
    "합계": 570647,
    "원자력": 133505,
    "화력": 397494,
    "수력": 3911,
    "신재생 및 기타": 35736
  },
  "2019": {
    "합계": 570721,
    "원자력": 145910,
    "화력": 375031,
    "수력": 3458,
    "신재생 및 기타": 46322
  },
  "2020": {
    "합계": 547797,
    "원자력": 160184,
    "화력": 344499,
    "수력": 3271,
    "신재생 및 기타": 39843
  },
  "2021": {
    "합계": 576809,
    "원자력": 158015,
    "화력": 368699,
    "수력": 3683,
    "신재생 및 기타": 46412
  },
  "2022": {
    "합계": 594400,
    "원자력": 176054,
    "화력": 358772,
    "수력": 3715,
    "신재생 및 기타": 55860
  },
  "2023": {
    "합계": 588047,
    "원자력": 180494,
    "화력": 344163,
    "수력": 3784,
    "신재생 및 기타": 59606
  }
}